[
  {
    "v": 1,
    "t": "Eis as etapas que fizeram os israe­litas desde a sua partida do Egito em tropas organizadas sob as ordens de Moisés e Aarão."
  },
  {
    "v": 2,
    "t": "Moisés, por or­dem do Senhor, tomou nota de suas marchas por etapas. São as seguintes essas marchas em etapas:"
  },
  {
    "v": 3,
    "t": "No décimo quinto dia do primeiro mês partiram de Ramsés. Isso foi no dia seguinte à Páscoa; partiram com a mão levantada, à vista de todos os egípcios"
  },
  {
    "v": 4,
    "t": "que estavam enterrando aqueles que o Senhor tinha ferido dentre eles, todos os seus primogê­nitos. Também contra os seus deuses o Senhor tinha exercido o seu juízo."
  },
  {
    "v": 5,
    "t": "Partidos de Ramsés, os israelitas se detiveram em Sucot,"
  },
  {
    "v": 6,
    "t": "de onde partiram, indo acampar em Etam, situado na extremidade do deserto."
  },
  {
    "v": 7,
    "t": "Dali, voltaram a Piairot, defronte de Baal Sefon, e acamparam diante de Magdol."
  },
  {
    "v": 8,
    "t": "Deixando Piairot, passaram pelo meio do mar para o deserto. Após três dias de marcha na solidão de Etam, detiveram-se em Mara."
  },
  {
    "v": 9,
    "t": "Partindo de Mara, ganharam Elim, onde havia doze fontes e setenta palmeiras; e acamparam ali."
  },
  {
    "v": 10,
    "t": "Saindo de Elim, foram acampar junto do mar Vermelho,"
  },
  {
    "v": 11,
    "t": "de onde partiram e acamparam no deserto de Sin."
  },
  {
    "v": 12,
    "t": "Tendo partido do deserto de Sin, acamparam em Dafca,"
  },
  {
    "v": 13,
    "t": "de onde foram para Alus."
  },
  {
    "v": 14,
    "t": "Dali, partiram e acamparam em Rafidim, onde o povo não encontrou água para beber."
  },
  {
    "v": 15,
    "t": "Partidos de Rafidim, acamparam no deserto do Sinai."
  },
  {
    "v": 16,
    "t": "Saindo do deserto do Sinai, foram acampar em Kibrot-Hataava,"
  },
  {
    "v": 17,
    "t": "de onde foram acampar em Haserot."
  },
  {
    "v": 18,
    "t": "De lá, acamparam em Retma."
  },
  {
    "v": 19,
    "t": "De Retma foram a Remon­-Farés."
  },
  {
    "v": 20,
    "t": "De Remon-Farés a Lebna."
  },
  {
    "v": 21,
    "t": "De Lebna a Ressa."
  },
  {
    "v": 22,
    "t": "De Ressa a Ceelata."
  },
  {
    "v": 23,
    "t": "Deixaram Ceelata e acamparam no monte Sefer."
  },
  {
    "v": 24,
    "t": "Dali foram acampar em Arada."
  },
  {
    "v": 25,
    "t": "De lá a Macelot."
  },
  {
    "v": 26,
    "t": "Dali a Taat."
  },
  {
    "v": 27,
    "t": "De Taat a Taré."
  },
  {
    "v": 28,
    "t": "De Taré a Metca."
  },
  {
    "v": 29,
    "t": "De Metca a Hesmona."
  },
  {
    "v": 30,
    "t": "De Hesmona foram acampar em Moserot.*"
  },
  {
    "v": 31,
    "t": "De Moserot a Benê-Jacã."
  },
  {
    "v": 32,
    "t": "Dali a Hor-Guidgad."
  },
  {
    "v": 33,
    "t": "Dali a Jotebata."
  },
  {
    "v": 34,
    "t": "Dali a Abrona."
  },
  {
    "v": 35,
    "t": "De lá a Asiongaber."
  },
  {
    "v": 36,
    "t": "De Asiongaber foram acampar no deserto de Sin, isto é, em Cades."
  },
  {
    "v": 37,
    "t": "Deixando Cades, acamparam no monte Hor, na extremidade da terra de Edom."
  },
  {
    "v": 38,
    "t": "O sacerdote Aarão subiu por ordem do Senhor ao monte Hor e ali morreu, no qua­dragésimo ano do êxodo dos israelitas do Egito, no primeiro dia do quinto mês."
  },
  {
    "v": 39,
    "t": "Aarão tinha cento e vinte e três anos quando expirou no monte Hor."
  },
  {
    "v": 40,
    "t": "Foi então que o rei cananeu de Arad, que habitava no Negueb, na terra de Canaã, soube da chegada dos israelitas."
  },
  {
    "v": 41,
    "t": "Deixando o monte Hor acamparam em Salmona."
  },
  {
    "v": 42,
    "t": "De Salmona foram acampar em Funon."
  },
  {
    "v": 43,
    "t": "De Funon foram a Obot."
  },
  {
    "v": 44,
    "t": "De Obot, detiveram-se em Ijé-Aba­rim, na fronteira de Moab."
  },
  {
    "v": 45,
    "t": "Dali foram acampar em Dibon-Gad."
  },
  {
    "v": 46,
    "t": "Dali a Almon-Diblataim."
  },
  {
    "v": 47,
    "t": "Dali aos montes Abarim, em frente ao Nebo."
  },
  {
    "v": 48,
    "t": "Partiram dos montes Aba­rim e foram acampar nas planícies de Moab, junto do Jordão, defronte de Jericó."
  },
  {
    "v": 49,
    "t": "Seu acampamento nas planícies de Moab, perto do Jordão, ia desde Bet-Jesimot até Abel-Setim."
  },
  {
    "v": 50,
    "t": "O Senhor disse a Moisés, nas planícies de Moab, junto do Jordão, defronte de Jericó:"
  },
  {
    "v": 51,
    "t": "“Dize aos israelitas: Quando tiverdes passado o Jordão e entrado na terra de Canaã,"
  },
  {
    "v": 52,
    "t": "expulsareis de diante de vós todos os habitantes da terra, destruireis todas as suas pedras esculpidas, todas as suas estátuas fundidas e devastareis todos os seus lugares altos."
  },
  {
    "v": 53,
    "t": "Tomareis posse da terra e habitai-a, porque vo-la dou."
  },
  {
    "v": 54,
    "t": "Distribuí entre vossas famílias por sorte: aos que forem mais numerosos, uma porção maior, e uma menor, aos que forem menos. Cada um possuirá o que lhe couber por sorte. Fareis essa repartição segundo vossas tribos patriarcais."
  },
  {
    "v": 55,
    "t": "Se vós, porém, não expulsardes de diante de vós os habitantes da terra, os que ficarem serão para vós como espinhos nos olhos e aguilhões nos flancos, e vos perseguirão na terra onde habitardes."
  },
  {
    "v": 56,
    "t": "E tudo o que eu tinha pensado fazer a eles, o farei a vós”."
  }
]