[{"v": 1, "t": "Eliú, falando de novo, disse:"}, {"v": 2, "t": "Parece-te porventura justo o teu pensamento, quando disseste: Eu tenho razão contra Deus?"}, {"v": 3, "t": "Ou quando disseste: de que me serve a minha inocência, que vantagem tirei de não pecar?"}, {"v": 4, "t": "Eu, portanto, responderei aos teus discursos e aos teus amigos contigo."}, {"v": 5, "t": "Levanta os olhos ao céu e vê, contempla como o firmamento é mais alto que tu."}, {"v": 6, "t": "Se pecares, que dano farás tu a Deus? Se as tuas iniquidades se multiplicarem, que prejuízo lhe causarás?"}, {"v": 7, "t": "Se obrares com justiça, que proveito lhe darás ou que receberá ele da tua mão?"}, {"v": 8, "t": "A tua impiedade só poderá fazer mal a um homem, que é teu semelhante; a tua justiça só poderá ser útil ao afilho do homem."}, {"v": 9, "t": "Eles (os oprimidos) clamam por causa da gravidade da opressão, e lamentam-se por causa da violência do braço dos tiranos."}, {"v": 10, "t": "Mas nenhum disse: Onde está o Deus que me criou, que inspira cânticos de júbilo em plena noite;"}, {"v": 11, "t": "que nos instrui mais que aos animais da terra, e nos ilustra mais que às aves do céu?"}, {"v": 12, "t": "Clamam então, e Deus não os ouve por causa da soberba dos maus."}, {"v": 13, "t": "Deus não ouve gritos vãos o Omnipotente não os atende."}, {"v": 14, "t": "Ainda quando tenhas dito: \"(Deus\") não atende\", — a (tua) causa está já diante dele, espera o seu julgamento."}, {"v": 15, "t": "Mas, agora, porque a sua cólera ainda se não manifestou, há motivo para dizer que ele não faz caso do crime?"}, {"v": 16, "t": "Logo Job em vão abriu a sua boca, insensatamente multiplicou palavras."}]