[
  {
    "v": 1,
    "t": "Ao mestre de canto. Com instrumentos de corda. Salmo. Cântico.*"
  },
  {
    "v": 2,
    "t": "Tenha Deus piedade de nós e nos abençoe, faça resplandecer sobre nós a luz da sua face,"
  },
  {
    "v": 3,
    "t": "para que se conheçam na terra os seus caminhos e em todas as nações a sua salvação.*"
  },
  {
    "v": 4,
    "t": "Que os povos vos louvem, ó Deus, que todos os povos vos glorifiquem."
  },
  {
    "v": 5,
    "t": "Alegrem-se e exultem as nações, porquanto com equidade regeis os povos e dirigis as nações sobre a terra."
  },
  {
    "v": 6,
    "t": "Que os povos vos louvem, ó Deus, que todos os povos vos glorifiquem."
  },
  {
    "v": 7,
    "t": "A terra deu o seu fruto, abençoou-nos o Senhor, nosso Deus."
  },
  {
    "v": 8,
    "t": "Sim, que Deus nos abençoe, e que o reverenciem até os confins da terra."
  }
]