[{"v": 1, "t": "Ao mestre do coro. Segundo a melodia do cântico \"Os Lagares\" ... Salmo. De Davide."}, {"v": 2, "t": "Senhor, Senhor nosso, quão admirável é o teu nome em toda a terra, tu que elevaste a tua majestade acima dos céus."}, {"v": 3, "t": "Da boca das crianças e meninos de peito fizeste sair louvor contra os teus adversários, para reprimir o inimigo e o agressor. (ver nota)"}, {"v": 4, "t": "Quando contemplo os teus céus, obra dos teus dedos, a lua e as estrelas, que tu criaste,"}, {"v": 5, "t": "(exclamo): Que é o homem, para te lembrares dele? ou que é o filho do homem, para cuidares dele?"}, {"v": 6, "t": "Tu o fizeste pouco inferior aos anjos, de glória e de honra o coroaste;"}, {"v": 7, "t": "deste-lhe o mando sobre as obras das tuas mãos, sujeitaste todas as coisas debaixo de seus pés:"}, {"v": 8, "t": "Todas as ovelhas e todos os bois e, além destes, os outros animais do campo,"}, {"v": 9, "t": "as aves do céu e os peixes do mar: tudo o que percorre as veredas dos oceanos."}, {"v": 10, "t": "Senhor, Senhor nosso, quão admirável é o teu nome em toda a terra!"}]