[
  {
    "v": 1,
    "t": "I praise You, O Lord, because I love You."
  },
  {
    "v": 2,
    "t": "O Most High, forsake me not, for You are my hope."
  },
  {
    "v": 3,
    "t": "Freely did I receive Your grace, may I live by it."
  },
  {
    "v": 4,
    "t": "My persecutors will come but let them not see me."
  },
  {
    "v": 5,
    "t": "Let a cloud of darkness fall upon their eyes; and let an air of thick darkness obscure them."
  },
  {
    "v": 6,
    "t": "And let them have no light to see, so that they cannot seize me."
  },
  {
    "v": 7,
    "t": "Let their designs become hardened, so that whatever they have conspired shall return upon their own heads."
  },
  {
    "v": 8,
    "t": "For they have devised a plan, but it was not for them."
  },
  {
    "v": 9,
    "t": "They prepared themselves maliciously, but they were found to be impotent."
  },
  {
    "v": 10,
    "t": "Indeed my confidence is upon the Lord, and I will not fear."
  },
  {
    "v": 11,
    "t": "And because the Lord is my salvation, I will not fear."
  },
  {
    "v": 12,
    "t": "And He is as a woven crown upon my head, and I shall not be shaken."
  },
  {
    "v": 13,
    "t": "Even if everything should be shaken, I shall stand firm."
  },
  {
    "v": 14,
    "t": "And though all things visible should perish, I shall not die;"
  },
  {
    "v": 15,
    "t": "Because the Lord is with me, and I with Him."
  },
  {
    "v": 16,
    "t": "Hallelujah."
  }
]