[
  {
    "v": 0,
    "t": "Frags. 3 Col. iii + 4"
  },
  {
    "v": 1,
    "t": "and he brought out [...]"
  },
  {
    "v": 2,
    "t": "and this very day[...]"
  },
  {
    "v": 3,
    "t": "and we listened to Moses [...]"
  },
  {
    "v": 4,
    "t": "a just and great man [... chiefs of thousands, chiefs of]"
  },
  {
    "v": 5,
    "t": "hundreds, chiefs of fif[ties and chiefs of tens ... to the judges]"
  },
  {
    "v": 6,
    "t": "and (to) the inspectors [...]"
  },
  {
    "v": 7,
    "t": "he will listen and not [...]"
  },
  {
    "v": 8,
    "t": "and do not be afraid, be strong and re[solute becau]se you will cause [this people] to take possession [... he will not]"
  },
  {
    "v": 9,
    "t": "leave you or desert [you. Let] your hands be strong [...]"
  },
  {
    "v": 10,
    "t": "to set out in [front of the people ...]"
  }
]